qwilprobe/__init__.py
qwilprobe/__main__.py
qwilprobe/main.py
qwilprobe/client/__init__.py
qwilprobe/client/probe.py
qwilprobe/generated/__init__.py
qwilprobe/generated/qwilprobe_pb2.py
qwilprobe/generated/qwilprobe_pb2_grpc.py
qwilprobe/service/__init__.py
qwilprobe/service/api.py
qwilprobe/service/microservice.py
qwilprobe/shared/__init__.py
qwilprobe/shared/constants.py
qwilprobe/shared/util.py
qwilprobe-0.3.0.dist-info/LICENSE
qwilprobe-0.3.0.dist-info/METADATA
qwilprobe-0.3.0.dist-info/WHEEL
qwilprobe-0.3.0.dist-info/top_level.txt
qwilprobe-0.3.0.dist-info/RECORD
