Metadata-Version: 2.1
Name: qwilprobe
Version: 0.3.0
Summary: Probe microservice library for Qwilfish
Home-page: https://gitlab.com/zluudg/qwilprobe
Author: zluudg
Author-email: 8853567-zluudg@users.noreply.gitlab.com
Classifier: Programming Language :: Python :: 3
Classifier: Development Status :: 2 - Pre-Alpha
Classifier: License :: OSI Approved :: MIT License
Requires-Python: >=3.8
License-File: LICENSE
Requires-Dist: protobuf (>=3.19.0)
Requires-Dist: grpcio (>=1.43.0)
Provides-Extra: dev
Requires-Dist: pytest (>=7.1.2) ; extra == 'dev'
Requires-Dist: tox (>=3.25.0) ; extra == 'dev'
Requires-Dist: bump2version (>=1.0.1) ; extra == 'dev'
Requires-Dist: build (>=0.8.0) ; extra == 'dev'
Requires-Dist: isort (>=5.10.1) ; extra == 'dev'
Requires-Dist: sphinx (>=5.0.0) ; extra == 'dev'
Requires-Dist: flake8 (>=4.0.1) ; extra == 'dev'
